odoo8_addon_l10n_fr_state-8.0.0.1.2.99.dev4-py2.7-nspkg.pth
odoo8_addon_l10n_fr_state-8.0.0.1.2.99.dev4.dist-info/DESCRIPTION.rst
odoo8_addon_l10n_fr_state-8.0.0.1.2.99.dev4.dist-info/METADATA
odoo8_addon_l10n_fr_state-8.0.0.1.2.99.dev4.dist-info/RECORD
odoo8_addon_l10n_fr_state-8.0.0.1.2.99.dev4.dist-info/WHEEL
odoo8_addon_l10n_fr_state-8.0.0.1.2.99.dev4.dist-info/metadata.json
odoo8_addon_l10n_fr_state-8.0.0.1.2.99.dev4.dist-info/namespace_packages.txt
odoo8_addon_l10n_fr_state-8.0.0.1.2.99.dev4.dist-info/top_level.txt
odoo_addons/l10n_fr_state/__init__.py
odoo_addons/l10n_fr_state/__openerp__.py
odoo_addons/l10n_fr_state/data/res_country_state_data.yml
odoo_addons/l10n_fr_state/i18n/fr.po
odoo_addons/l10n_fr_state/i18n/l10n_fr_state.pot
odoo_addons/l10n_fr_state/migrations/8.0.0.1.1/pre-migration.py
odoo_addons/l10n_fr_state/migrations/8.0.0.1.2/post-migration.py
odoo_addons/l10n_fr_state/static/description/icon.png
odoo_addons/l10n_fr_state/static/src/img/screenshots/1.png
